lapa_authentication_helper/__init__.py
lapa_authentication_helper/configuration.py
lapa_authentication_helper/main.py
lapa_authentication_helper/data/config.ini
lapa_authentication_helper-0.0.1.dist-info/METADATA
lapa_authentication_helper-0.0.1.dist-info/WHEEL
lapa_authentication_helper-0.0.1.dist-info/top_level.txt
lapa_authentication_helper-0.0.1.dist-info/RECORD
