Metadata-Version: 2.1
Name: lapa-authentication-helper
Version: 0.0.1
Summary: helper to access the authentication service.
Home-page: https://github.com/thepmsquare/lapa_authentication_helper
Author: Amish Palkar
Author-email: amishpalkar302001@gmail.com
License: UNKNOWN
Platform: UNKNOWN
Classifier: Development Status :: 3 - Alpha
Classifier: Intended Audience :: Developers
Classifier: License :: OSI Approved :: MIT License
Classifier: Programming Language :: Python :: 3
Classifier: Programming Language :: Python :: 3.9
Requires-Dist: requests >=2.31.0
